Workbook

Sheet Cover
A1: UK FINANCIAL SERVICES
A2: KPI Analytics Model — FY 2022–2024
A3: Analyst: Attic C. Lee · Three sectors: Asset Management · Retail Banking · Insurance
A7: COLOUR CODING LEGEND
A8: Blue text | C8: Hardcoded inputs — change these for scenarios
A9: Black text | C9: Formulas — calculated automatically
A10: Green text | C10: Cross-sheet links — pulling from another tab
A11: Yellow bg | C11: Key assumptions requiring review / update
A14: SHEET INDEX
A15: Cover | C15: This page — legend and sheet guide
A16: Assumptions | C16: Key model inputs — edit here for scenarios
A17: AM_Performance | C17: Asset management — AUM, returns, active alpha
A18: RB_Revenue | C18: Retail banking — product revenue, CIR, NPS
A19: Ins_Ratios | C19: Insurance — loss ratio, combined ratio, GWP
A20: Group_Summary | C20: Cross-sector KPI summary — executive view

Sheet Assumptions
A1: Model Assumptions — Edit here for scenario analysis
A2: ASSET MANAGEMENT
A3: Target equity fund return (annual %) | B3: 0.08 | C3: Industry benchmark: ~8% for active equity
A4: Target fixed income return (annual %) | B4: 0.04 | C4: IG bond market average
A5: Average management fee (bps) | B5: 65 | C5: Institutional rate range: 40–120bps
A6: Hurdle rate for performance fees | B6: 0.05 | C6: 5% above which perf fees apply
A7: AUM growth target (annual %) | B7: 0.07 | C7: Organic + net inflows assumption
A8: RETAIL BANKING
A9: Net interest margin (%) | B9: 0.021 | C9: UK bank NIM avg 2024: ~2.1%
A10: Cost-income ratio target | B10: 0.6 | C10: Sector benchmark: 55–65%
A11: Digital adoption target (%) | B11: 0.85 | C11: Strategy goal by end 2024
A12: NPS target score | B12: 40 | C12: UK FS sector average: 30–45
A13: Customer churn rate assumption (%) | B13: 0.015 | C13: Monthly churn rate
A14: INSURANCE
A15: Target combined ratio | B15: 0.95 | C15: <100% = underwriting profit
A16: Target loss ratio | B16: 0.62 | C16: UK motor market avg: ~65%
A17: Target expense ratio | B17: 0.28 | C17: Efficiency target
A18: GWP growth target (annual %) | B18: 0.06 | C18: Market rate inflation + new business
A19: Reserve adequacy minimum (%) | B19: 1 | C19: Reserves >= 100% of expected claims

Sheet AM_Performance
A1: Asset Management — Annual Fund Performance Summary (£mm AUM)
A2: Fund Name | B2: Asset Class | C2: 2022 AUM | D2: 2023 AUM | E2: 2024 AUM | F2: 2022 Return% | G2: 2023 Return% | H2: 2024 Return%
A3: ESG Multi-Asset Fund | B3: Multi-Asset | C3: 436.7 | D3: 460.3 | E3: 527.4 | F3: -0.0718 | G3: -0.1192 | H3: 0.09
A4: Global Bond Income Fund | B4: Fixed Income | C4: 651.7 | D4: 712.7 | E4: 786.9 | F4: 0.0155 | G4: 0.0408 | H4: 0.0285
A5: Infrastructure Debt Fund | B5: Alternatives | C5: 412.4 | D5: 490.6 | E5: 638 | F5: 0.0114 | G5: 0.1662 | H5: 0.0816
A6: Short Duration Credit Fund | B6: Fixed Income | C6: 298.8 | D6: 364.6 | E6: 478 | F6: -0.0197 | G6: 0.083 | H6: 0.116
A7: UK Equity Growth Fund | B7: Equity | C7: 870.7 | D7: 1017.5 | E7: 1254.4 | F7: -0.0015 | G7: 0.2473 | H7: 0.0723
A8: US Large Cap Fund | B8: Equity | C8: 1236.5 | D8: 1304.1 | E8: 1314.1 | F8: 0.1737 | G8: -0.0279 | H8: -0.0138
A10: Total AUM / Portfolio Return (all funds)
A11: TOTAL / AVERAGE | C11: =SUM(C3:C9) -> 3906.8 | D11: =SUM(D3:D9) -> 4349.8 | E11: =SUM(E3:E9) -> 4998.8 | F11: =AVERAGE(F3:F9) -> 0.017933333 | G11: =AVERAGE(G3:G9) -> 0.065033333 | H11: =AVERAGE(H3:H9) -> 0.062433333
A13: Active Return vs Benchmark (annual basis points)
A14: Fund Name | B14: 2022 Active Ret | C14: 2023 Active Ret | D14: 2024 Active Ret | E14: 3Y Avg
A15: ESG Multi-Asset Fund | B15: 1012.2 | C15: -2504.7 | D15: -918 | E15: =AVERAGE(B15:D15) -> -803.5
A16: Global Bond Income Fund | B16: 1190.6 | C16: 751.1 | D16: 649.9 | E16: =AVERAGE(B16:D16) -> 863.86667
A17: Infrastructure Debt Fund | B17: -721.9 | C17: 1258.8 | D17: 1215.5 | E17: =AVERAGE(B17:D17) -> 584.13333
A18: Short Duration Credit Fund | B18: 65.8 | C18: 313.4 | D18: 378.8 | E18: =AVERAGE(B18:D18) -> 252.66667
A19: UK Equity Growth Fund | B19: 585.8 | C19: -586.1 | D19: -2855.6 | E19: =AVERAGE(B19:D19) -> -951.96667
A20: US Large Cap Fund | B20: 1426 | C20: 358.3 | D20: -2876.7 | E20: =AVERAGE(B20:D20) -> -364.13333

Sheet RB_Revenue
A1: Retail Banking — Annual Product Revenue & KPIs
A2: Product | B2: Segment | C2: 2022 Rev(£k) | D2: 2023 Rev(£k) | E2: 2024 Rev(£k) | F2: 2024 NPS | G2: 2024 CIR | H2: 2024 Digital% | I2: Rev Growth 22→24
A3: Credit Cards | B3: Personal | C3: 73992.5 | D3: 78154.7 | E3: 79886.9 | F3: 29.2 | G3: 0.61166667 | H3: 0.71941667 | I3: =(E3-C3)/C3 -> 0.079662128
A4: Current Accounts | B4: Personal | C4: 49462.8 | D4: 52315.4 | E4: 54263.4 | F4: 30.3 | G4: 0.60216667 | H4: 0.725 | I4: =(E4-C4)/C4 -> 0.097054756
A5: Mortgages | B5: Personal | C5: 147809.5 | D5: 154389.4 | E5: 162001.6 | F5: 33 | G5: 0.61033333 | H5: 0.72433333 | I5: =(E5-C5)/C5 -> 0.096016156
A6: Personal Loans | B6: Personal | C6: 68290.2 | D6: 73028.7 | E6: 75791.7 | F6: 29.2 | G6: 0.62916667 | H6: 0.71441667 | I6: =(E6-C6)/C6 -> 0.10984739
A7: SME Business Accounts | B7: Business | C7: 45254.7 | D7: 48122.8 | E7: 49774.2 | F7: 33.2 | G7: 0.63983333 | H7: 0.73333333 | I7: =(E7-C7)/C7 -> 0.09986808
A8: SME Lending | B8: Business | C8: 83656.2 | D8: 88753.4 | E8: 92874.5 | F8: 28.7 | G8: 0.61075 | H8: 0.70366667 | I8: =(E8-C8)/C8 -> 0.11019267
A9: Savings Accounts | B9: Personal | C9: 36651.3 | D9: 39076.3 | E9: 40281 | F9: 30.2 | G9: 0.64058333 | H9: 0.71025 | I9: =(E9-C9)/C9 -> 0.099033322
A10: Trade Finance | B10: Business | C10: 48243.1 | D10: 51577.5 | E10: 52326.8 | F10: 32.5 | G10: 0.61708333 | H10: 0.74241667 | I10: =(E10-C10)/C10 -> 0.084648375
A12: Total Revenue by Segment
A13: Personal | C13: =SUMIF($B$3:$B$11,"Personal",C$3:C$11) -> 376206.3 | D13: =SUMIF($B$3:$B$11,"Personal",D$3:D$11) -> 396964.5 | E13: =SUMIF($B$3:$B$11,"Personal",E$3:E$11) -> 412224.6
A14: Business | C14: =SUMIF($B$3:$B$12,"Business",C$3:C$12) -> 177154 | D14: =SUMIF($B$3:$B$12,"Business",D$3:D$12) -> 188453.7 | E14: =SUMIF($B$3:$B$12,"Business",E$3:E$12) -> 194975.5
A15: TOTAL | C15: =SUM(C3:C13) -> 929566.6 | D15: =SUM(D3:D13) -> 982382.7 | E15: =SUM(E3:E13) -> 1019424.7

Sheet Ins_Ratios
A1: Insurance — Annual Ratios & Underwriting Performance
A2: Line of Business | B2: 2022 GWP(£k) | C2: 2023 GWP(£k) | D2: 2024 GWP(£k) | E2: 2024 Loss Ratio | F2: 2024 Exp Ratio | G2: 2024 Combined | H2: 2024 UW Profit(£k) | I2: Renewal Rate
A3: Commercial Property | B3: 73738.3 | C3: 78842.3 | D3: 80283.2 | E3: 0.59871667 | F3: 0.248825 | G3: 0.84754167 | H3: 12241.3 | I3: 0.84241667
A4: Cyber | B4: 26044.7 | C4: 27975.4 | D4: 30384.6 | E4: 0.65714167 | F4: 0.3146 | G4: 0.97174167 | H4: 866.3 | I4: 0.84825
A5: Health & Protection | B5: 55889.7 | C5: 59121.9 | D5: 60350.6 | E5: 0.72426667 | F5: 0.21810833 | G5: 0.942375 | H5: 3510.9 | I5: 0.82941667
A6: Home | B6: 63210.2 | C6: 66352.4 | D6: 69952.9 | E6: 0.60976667 | F6: 0.30299167 | G6: 0.91275833 | H6: 6092.9 | I6: 0.84391667
A7: Liability | B7: 46660.8 | C7: 48515.9 | D7: 50179.3 | E7: 0.57175833 | F7: 0.26805 | G7: 0.83980833 | H7: 8026.8 | I7: 0.85441667
A8: Motor | B8: 104826.2 | C8: 112796.2 | D8: 122537.6 | E8: 0.69136667 | F8: 0.2776 | G8: 0.96896667 | H8: 3920.5 | I8: 0.84958333
A10: Portfolio Totals / Weighted Averages
A11: TOTAL PORTFOLIO | B11: =SUM(B3:B9) -> 370369.9 | C11: =SUM(C3:C9) -> 393604.1 | D11: =SUM(D3:D9) -> 413688.2 | E11: =AVERAGE(E3:E9) -> 0.64216944 | F11: =AVERAGE(F3:F9) -> 0.27169583 | G11: =AVERAGE(G3:G9) -> 0.91386528 | H11: =SUM(H3:H9) -> 34658.7 | I11: =AVERAGE(I3:I9) -> 0.84466667

Sheet Group_Summary
A1: Group KPI Summary — Cross-Sector Executive View (FY 2024)
A2: KPI | B2: Asset Management | C2: Retail Banking | D2: Insurance | E2: Notes
A3: REVENUE / AUM
A4: Total AUM / Revenue (£k, 2024) | B4: =AM_Performance!E16 -> 863.86667 | C4: =RB_Revenue!E16 -> 0 | D4: =Ins_Ratios!D9 -> 0 | E4: Cross-sector totals
A5: YoY Revenue Growth | B5: — | C5: =RB_Revenue!I3 -> 0.079662128 | D5: =(Ins_Ratios!D3-Ins_Ratios!B3)/Ins_Ratios!B3 -> 0.088758488 | E5: 2022→2024
A6: PROFITABILITY
A7: Cost-Income Ratio (2024) | B7: — | C7: =RB_Revenue!G3 -> 0.61166667 | D7: — | E7: Target: <60%
A8: Combined Ratio (2024 avg) | B8: — | C8: — | D8: =Ins_Ratios!G16 -> 0 | E8: Target: <100%
A9: CUSTOMER METRICS
A10: NPS Score (2024 avg) | B10: — | C10: =RB_Revenue!F3 -> 29.2 | D10: — | E10: Target: >40
A11: Renewal Rate (2024 avg) | B11: — | C11: — | D11: =Ins_Ratios!I3 -> 0.84241667 | E11: Target: >85%
A12: RISK
A13: Active Return vs Benchmark (bps) | B13: =AM_Performance!E25 -> 0 | C13: — | D13: — | E13: Positive = alpha generation
